revo_snd/__init__.py
revo_snd/nw4r.py
revo_snd/nw4r_err.py
revo_snd/adpcm/__init__.py
revo_snd/adpcm/adpcm.py
revo_snd/adpcm/encode_adpcm.py
revo_snd/engine/OS.py
revo_snd/engine/OS_Sound.py
revo_snd/engine/__init__.py
revo_snd/engine/seq/OS_SeqPlayer.py
revo_snd/engine/seq/__init__.py
revo_snd/engine/wav/OS_WaveSound.py
revo_snd/engine/wav/__init__.py
revo_snd/rbnk/__init__.py
revo_snd/rbnk/brbnk.py
revo_snd/rsar/__init__.py
revo_snd/rsar/brsar.py
revo_snd/rsar/file.py
revo_snd/rsar/info.py
revo_snd/rsar/string_trie.py
revo_snd/rsar/symbol.py
revo_snd/rseq/__init__.py
revo_snd/rseq/brseq.py
revo_snd/rseq/midi.py
revo_snd/rseq/mml_instruction.py
revo_snd/rseq/mml_parser.py
revo_snd/rseq/note.py
revo_snd/rstm/__init__.py
revo_snd/rstm/brstm.py
revo_snd/rwar/__init__.py
revo_snd/rwar/brwar.py
revo_snd/rwav/__init__.py
revo_snd/rwav/brwav.py
revo_snd/rwsd/__init__.py
revo_snd/rwsd/brwsd.py
revo_snd-0.1.16.dist-info/LICENSE
revo_snd-0.1.16.dist-info/METADATA
revo_snd-0.1.16.dist-info/WHEEL
revo_snd-0.1.16.dist-info/top_level.txt
revo_snd-0.1.16.dist-info/RECORD
