Metadata-Version: 2.2
Name: revo-snd
Version: 0.1.16
Summary: Your entire toolset for editing Nintendo Wii sound files
Author: Ogu99
License: MIT License
Classifier: Programming Language :: Python :: 3
Classifier: Operating System :: OS Independent
Requires-Python: >=3.11
License-File: LICENSE
Requires-Dist: numpy
Requires-Dist: numba
Requires-Dist: sounddevice
